lib/__init__.py
lib/bingenum.py
lib/crtenum.py
lib/dnshelper.py
lib/msf_print.py
lib/whois.py
lib/yandexenum.py
recondns/__init__.py
recondns/recondns.py
recondns/lib/__init__.py
recondns/lib/bingenum.py
recondns/lib/crtenum.py
recondns/lib/dnshelper.py
recondns/lib/msf_print.py
recondns/lib/whois.py
recondns/lib/yandexenum.py
reconDNS-0.0.3.dist-info/METADATA
reconDNS-0.0.3.dist-info/WHEEL
reconDNS-0.0.3.dist-info/top_level.txt
reconDNS-0.0.3.dist-info/RECORD
