Metadata-Version: 2.1
Name: reconDNS
Version: 0.0.3
Summary: DNS Enumeration Script
Home-page: https://github.com/f8al/dnsrecon
Author: @SecurityShrimp
License: UNKNOWN
Platform: UNKNOWN
Classifier: Programming Language :: Python :: 3
Classifier: Programming Language :: Python :: 3.6
Classifier: Programming Language :: Python :: 3.7
Classifier: Programming Language :: Python :: 3.8
Classifier: License :: OSI Approved :: GNU General Public License v2 (GPLv2)
Classifier: Operating System :: OS Independent
Requires: dnspython
Requires: netaddr
Requires: lxml
Requires: flake8
Requires-Python: >=3.6
